vid_cut/__init__.py
vid_cut/build_ffmpeg.py
vid_cut/get_video_duration.py
vid_cut/vidcut.py
vid_cut-0.1.2.dist-info/LICENSE
vid_cut-0.1.2.dist-info/METADATA
vid_cut-0.1.2.dist-info/WHEEL
vid_cut-0.1.2.dist-info/entry_points.txt
vid_cut-0.1.2.dist-info/RECORD
