Metadata-Version: 2.1
Name: vid-cut
Version: 0.1.2
Summary: A package for editing video files.
License: MIT
Author: MrMultiMediator
Requires-Python: >=3.7,<4.0
Classifier: License :: OSI Approved :: MIT License
Classifier: Programming Language :: Python :: 3
Classifier: Programming Language :: Python :: 3.7
Classifier: Programming Language :: Python :: 3.8
Classifier: Programming Language :: Python :: 3.9
Classifier: Programming Language :: Python :: 3.10
Classifier: Programming Language :: Python :: 3.11
Requires-Dist: docopt (>=0.6.2,<0.7.0)
